cmku_client/__init__.py
cmku_client/client.py
cmku_client/lib/__init__.py
cmku_client/lib/cache.py
cmku_client/lib/declass.py
cmku_client/lib/exceptions.py
cmku_client/lib/loader.py
cmku_client/lib/vars.py
cmku_client/model/__init__.py
cmku_client/model/action.py
cmku_client/model/breed.py
cmku_client-0.1.0.dist-info/METADATA
cmku_client-0.1.0.dist-info/WHEEL
cmku_client-0.1.0.dist-info/top_level.txt
cmku_client-0.1.0.dist-info/RECORD
