Metadata-Version: 2.1
Name: cmku-client
Version: 0.1.0
Summary: Client to access CMKU data
Home-page: https://github.com/westwardharbor0/cmku-client
Author: westwardharbor0
Author-email: westwardharbor0@gmail.com
License: UNKNOWN
Platform: UNKNOWN
